aiomodrinth/__init__.py
aiomodrinth/_requests.py
aiomodrinth/aiomodrinth.egg-info/dependency_links.txt
aiomodrinth/aiomodrinth.egg-info/PKG-INFO
aiomodrinth/aiomodrinth.egg-info/SOURCES.txt
aiomodrinth/aiomodrinth.egg-info/top_level.txt
aiomodrinth/api.py
aiomodrinth/common.py
aiomodrinth/exceptions.py
aiomodrinth/facets.py
aiomodrinth/license.py
aiomodrinth/models/enums.py
aiomodrinth/models/gallery.py
aiomodrinth/models/member.py
aiomodrinth/models/project.py
aiomodrinth/models/search.py
aiomodrinth/models/user.py
aiomodrinth/models/utils.py
aiomodrinth-0.1.1.dist-info/LICENSE
aiomodrinth-0.1.1.dist-info/WHEEL
aiomodrinth-0.1.1.dist-info/METADATA
aiomodrinth-0.1.1.dist-info/RECORD
